katapult/__init__.py
katapult/attrs.py
katapult/aws.py
katapult/cli.py
katapult/combopt.py
katapult/config_state.py
katapult/core.py
katapult/demo.py
katapult/isort/stdlibs/py39.py
katapult/maestroclient.py
katapult/maestroserver.py
katapult/provider.py
katapult/providerfat.py
katapult/providerlight.py
katapult/resources/instancetypes-aws.csv
katapult/resources/remote_files/bootstrap.sh
katapult/resources/remote_files/config.py
katapult/resources/remote_files/env_check.py
katapult/resources/remote_files/env_state.sh
katapult/resources/remote_files/getpid.sh
katapult/resources/remote_files/kill.sh
katapult/resources/remote_files/maestroenv.sh
katapult/resources/remote_files/microrun.sh
katapult/resources/remote_files/reset.sh
katapult/resources/remote_files/resetmaestro.sh
katapult/resources/remote_files/run.sh
katapult/resources/remote_files/startmaestro.sh
katapult/resources/remote_files/startserver.sh
katapult/resources/remote_files/state.sh
katapult/resources/remote_files/tail.sh
katapult/resources/remote_files/waitmaestro.sh
katapult/scriptflow/runner.py
katapult/utils.py
requirements.txt
katapult-0.6.23.dist-info/entry_points.txt
katapult-0.6.23.dist-info/WHEEL
katapult-0.6.23.dist-info/METADATA
katapult-0.6.23.dist-info/RECORD
