Metadata-Version: 2.1
Name: katapult
Version: 0.6.23
Summary: Katapult is a Python package that allows you to run any script on a cloud service (for now AWS only).
Home-page: https://github.com/benbenz/katapult
License: MIT
Author: Your Name
Author-email: you@example.com
Requires-Python: >=3.9,<4.0
Classifier: License :: OSI Approved :: MIT License
Classifier: Programming Language :: Python :: 3
Classifier: Programming Language :: Python :: 3.9
Classifier: Programming Language :: Python :: 3.10
Classifier: Programming Language :: Python :: 3.11
Provides-Extra: scriptflow
Requires-Dist: asyncssh (>=2.12.0,<2.13.0)
Requires-Dist: boto3 (==1.26.1)
Requires-Dist: jcs (>=0.2,<0.3)
Requires-Dist: ortools (>=9.0,<10.0)
Requires-Dist: psutil (>=5.9.4,<6.0.0)
Requires-Dist: pyyaml (>=6.0,<7.0)
Requires-Dist: scriptflow (>=0.2.5,<0.3.0); extra == "scriptflow"
Project-URL: Repository, https://github.com/benbenz/katapult
